README.md
setup.py
ecdsa/__init__.py
ecdsa/curves.py
ecdsa/point.py
ecdsa/private_key.py
ecdsa/public_key.py
ecdsa/signature.py
ecdsa/utils/__init__.py
ecdsa/utils/converter.py
ecdsa/utils/file.py
light_ecdsa.egg-info/PKG-INFO
light_ecdsa.egg-info/SOURCES.txt
light_ecdsa.egg-info/dependency_links.txt
light_ecdsa.egg-info/top_level.txt