Metadata-Version: 1.0
Name: light-ecdsa
Version: 1.0.1
Summary: Minimalistic ecdsa
Home-page: UNKNOWN
Author: 0xFrijolito
Author-email: <dante_torobolino@protonmail.com>
License: UNKNOWN
Keywords: python,ecdsa,signatures
Platform: UNKNOWN
